MANIFEST.in
README.md
setup.py
rotnotes/__init__.py
rotnotes/rotnotes.py
rotnotes.egg-info/PKG-INFO
rotnotes.egg-info/SOURCES.txt
rotnotes.egg-info/dependency_links.txt
rotnotes.egg-info/not-zip-safe
rotnotes.egg-info/top_level.txt