Metadata-Version: 1.0
Name: rotnotes
Version: 0.2
Summary: Script to rename your notes starting from 1 and rotate them so you can view them without rotating everytime
Home-page: http://github.com/light94/rename-notes
Author: light94
Author-email: iitkgp.rahulmishra@gmail.com
License: MIT
Platform: UNKNOWN
